<?xml version="1.0" encoding="UTF-8" ?>
<root>
    <!-- type="v" f="" t="" => from f to t -->
    <!-- type="l" a="" => a==axis:1=x,2=y -->
    <!-- type="d" => disable -->
    <item>
        <id>averageBlur</id>
        <scale type="v" f="1" t="255"/>
        <scale type="v" f="1" t="255"/>
        <scale type="d" />
        <scale type="d" />
    </item>
    <item>
        <id>medianBlur</id>
        <scale type="v" f="1" t="255"/>
        <scale type="d" />
        <scale type="d" />
        <scale type="d" />
    </item>
    <item>
        <id>bilateralFilterBlur</id>
        <scale type="v" f="1" t="255"/>
        <scale type="v" f="1" t="255"/>
        <scale type="v" f="1" t="255"/>
        <scale type="d" />
    </item>
    <item>
        <id>gaussianBlur</id>
        <scale type="v" f="1" t="255"/>
        <scale type="v" f="1" t="255"/>
        <scale type="v" f="1" t="255"/>
        <scale type="d" f="1" t="255"/>
    </item>
    <item>
        <id>laplacian</id>
        <scale type="d"/>
        <scale type="d"/>
        <scale type="d"/>
        <scale type="d"/>
    </item>
    <item>
        <id>sobel</id>
        <scale type="v" f="1" t="255"/>
        <scale type="v" f="1" t="31"/>
        <scale type="d"/>
        <scale type="d"/>
    </item>
    <item>
        <id>canny</id>
        <scale type="v" f="1" t="255"/>
        <scale type="v" f="1" t="255"/>
        <scale type="v" f="1" t="255"/>
        <scale type="d"/>
    </item>
    <item>
        <id>adaptiveThreshold</id>
        <scale type="v" f="1" t="255"/>
        <scale type="v" f="1" t="255"/>
        <scale type="v" f="1" t="255"/>
        <scale type="d"/>
    </item>
    <item>
        <id>globalThreshold</id>
        <scale type="v" f="0" t="255"/>
        <scale type="v" f="0" t="255"/>
        <scale type="d"/>
        <scale type="d"/>
    </item>
    <item>
        <id>watershedAlgorithm</id>
        <scale type="v" f="1" t="100"/>
        <scale type="d"/>
        <scale type="d"/>
        <scale type="d"/>
    </item>
    <item>
        <id>grabCutAlgorithm</id>
        <scale type="l" a="1"/>
        <scale type="l" a="0"/>
        <scale type="l" a="1"/>
        <scale type="l" a="0"/>
    </item>
    <item>
        <id>locationSelect</id>
        <scale type="l" a="1"/>
        <scale type="l" a="0"/>
        <scale type="l" a="1"/>
        <scale type="l" a="0"/>
    </item>
    <item>
        <id>harrisCornerDetection</id>
        <scale type="v" f="1" t="32"/>
        <scale type="v" f="1" t="31"/>
        <scale type="v" f="1" t="100"/>
        <scale type="v" f="1" t="50"/>
    </item>
    <item>
        <id>shiTomasiCornerDetection</id>
        <scale type="v" f="1" t="255"/>
        <scale type="v" f="1" t="100"/>
        <scale type="v" f="1" t="100"/>
        <scale type="d"/>
    </item>
    <item>
        <id>keypointDetection_SIFT</id>
        <scale type="d"/>
        <scale type="d"/>
        <scale type="d"/>
        <scale type="d"/>
    </item>
    <item>
        <id>keypointDetection_SURF</id>
        <scale type="d"/>
        <scale type="d"/>
        <scale type="d"/>
        <scale type="d"/>
    </item>
    <item>
        <id>keypointDetection_ORB</id>
        <scale type="v" f="1" t="500"/>
        <scale type="d"/>
        <scale type="d"/>
        <scale type="d"/>
    </item>
    <item>
        <id>RGB_model</id>
        <scale type="v" f="1" t="3"/> <!-- 1="Red" 2="Green" 3="Blue"-->
        <scale type="d"/>
        <scale type="d"/>
        <scale type="d"/>
    </item>
    <item>
        <id>CMY_model</id>
        <scale type="v" f="1" t="3"/> <!-- 1="Cyan" 2="Green" 3="Blue"-->
        <scale type="d"/>
        <scale type="d"/>
        <scale type="d"/>
    </item>
    <item>
        <id>HSI_model</id>
        <scale type="v" f="1" t="3"/> <!-- 1="" 2="" 3=""-->
        <scale type="d"/>
        <scale type="d"/>
        <scale type="d"/>
    </item>
    <item>
        <id>HSV_model</id>
        <scale type="v" f="1" t="3"/> <!-- 1="Hue" 2="Saturation" 3="Value"-->
        <scale type="d"/>
        <scale type="d"/>
        <scale type="d"/>
    </item>
    <item>
        <id>YCrCb_model</id>
        <scale type="v" f="1" t="3"/> <!-- 1="Y" 2="Cr" 3="Cb"-->
        <scale type="d"/>
        <scale type="d"/>
        <scale type="d"/>
    </item>
    <item>
        <id>RGB_histogram_equalization</id>
        <scale type="d"/>
        <scale type="d"/>
        <scale type="d"/>
        <scale type="d"/>
    </item>
    <item>
        <id>HSV_histogram_equalization</id>
        <scale type="d"/>
        <scale type="d"/>
        <scale type="d"/>
        <scale type="d"/>
    </item>
    <item>
        <id>ripple_effect</id>
        <scale type="v" f="1" t="4"/>
        <scale type="v" f="1" t="10"/>
        <scale type="v" f="1" t="10"/>
        <scale type="d"/>
    </item>
    <item>
        <id>fisheye_effect</id>
        <scale type="l" a="1"/>
        <scale type="l" a="0"/>
        <scale type="v" f="1" t="255"/>
        <scale type="d"/>
    </item>
    <item>
        <id>radial_pixelation</id>
        <scale type="v" f="1" t="10"/>
        <scale type="v" f="1" t="10"/>
        <scale type="d"/>
        <scale type="d"/>
    </item>
    <item>
        <id>twirl_effect</id>
        <scale type="v" f="-300" t="300"/>
        <scale type="d"/>
        <scale type="d"/>
        <scale type="d"/>
    </item>
    <item>
        <id>fuzzy_effect</id>
        <scale type="v" f="1" t="10"/>
        <scale type="d"/>
        <scale type="d"/>
        <scale type="d"/>
    </item>
    <item>
        <id>motion_blur</id>
        <scale type="v" f="1" t="255"/>
        <scale type="v" f="1" t="360"/>
        <scale type="d"/>
        <scale type="d"/>
    </item>
    <item>
        <id>radial_blur</id>
        <scale type="v" f="1" t="20"/>
        <scale type="d"/>
        <scale type="d"/>
        <scale type="d"/>
    </item>
    <item>
        <id>edge_preserving_filter</id>
        <scale type="v" f="1" t="2"/> <!-- 1="RECURS_FILTER" 2="NORMCONV_FILTER"-->
        <scale type="v" f="1" t="200"/>
        <scale type="v" f="1" t="100"/> <!-- 0 ~ 1-->
        <scale type="d"/>
    </item>
    <item>
        <id>detail_enhancement</id>
        <scale type="v" f="1" t="200"/>
        <scale type="v" f="1" t="100"/> <!-- 0 ~ 1-->
        <scale type="d"/>
        <scale type="d"/>
    </item>
    <item>
        <id>pencil_sketch</id>
        <scale type="v" f="1" t="200"/>
        <scale type="v" f="1" t="100"/>
        <scale type="v" f="1" t="100"/>
        <scale type="d"/>
    </item>
    <item>
        <id>stylization</id>
        <scale type="v" f="0" t="200"/>
        <scale type="v" f="0" t="100"/>
        <scale type="d"/>
        <scale type="d"/>
    </item>

</root>
